compneuro/__init__.py
compneuro/base_model.py
compneuro/errors.py
compneuro/types.py
compneuro/memristors/__init__.py
compneuro/memristors/hard_memristor.py
compneuro/memristors/potassium_channel_memristor.py
compneuro/memristors/sodium_channel_memristor.py
compneuro/memristors/soft_memristor.py
compneuro/neurons/__init__.py
compneuro/neurons/hodgkin_huxley.py
compneuro/neurons/hodgkin_huxley_3state.py
compneuro/neurons/hodgkin_huxley_rinzel.py
compneuro/neurons/hodgkin_huxley_wilson.py
compneuro/neurons/leaky_integrate_fire.py
compneuro/utils/__init__.py
compneuro/utils/plot.py
compneuro/utils/signal.py
compneuro/utils/bokeh/__init__.py
compneuro/utils/bokeh/plot3d.py
compneuro/utils/bokeh/plot3d_options.py
compneuro/utils/plotly/__init__.py
compneuro/utils/plotly/animate.py
compneuro/utils/plotly/plot3d.py
compneuro-0.1.2.dist-info/AUTHORS.rst
compneuro-0.1.2.dist-info/LICENSE
compneuro-0.1.2.dist-info/METADATA
compneuro-0.1.2.dist-info/WHEEL
compneuro-0.1.2.dist-info/top_level.txt
compneuro-0.1.2.dist-info/RECORD
