Metadata-Version: 2.1
Name: compneuro
Version: 0.1.2
Summary: Python Module for Book 4020
Home-page: https://github.com/TK-21st/CompNeuro
Author: Bionet Lab
Author-email: 
License: BSD license
Keywords: compneuro
Platform: UNKNOWN
Classifier: Development Status :: 2 - Pre-Alpha
Classifier: Intended Audience :: Developers
Classifier: License :: OSI Approved :: BSD License
Classifier: Natural Language :: English
Classifier: Programming Language :: Python :: 3
Classifier: Programming Language :: Python :: 3.7
Classifier: Programming Language :: Python :: 3.8
Classifier: Programming Language :: Python :: 3.9
Requires-Python: >=3.7
License-File: LICENSE
License-File: AUTHORS.rst
Requires-Dist: numpy
Requires-Dist: matplotlib
Requires-Dist: scipy
Requires-Dist: pylatexenc
Requires-Dist: bokeh
Requires-Dist: tqdm
Requires-Dist: plotly
Provides-Extra: dev
Requires-Dist: pylint ; extra == 'dev'
Requires-Dist: black ; extra == 'dev'
Requires-Dist: Sphinx ; extra == 'dev'
Requires-Dist: sphinx-autobuild ; extra == 'dev'
Provides-Extra: dist
Requires-Dist: pylint ; extra == 'dist'
Requires-Dist: black ; extra == 'dist'
Requires-Dist: Sphinx ; extra == 'dist'
Requires-Dist: sphinx-autobuild ; extra == 'dist'
Requires-Dist: twine ; extra == 'dist'
Requires-Dist: coverage ; extra == 'dist'
Requires-Dist: coverage-badge ; extra == 'dist'
